luna/__init__.py
luna/azuremlLunaUtils.py
luna/baseLunaUtils.py
luna/localLunaUtils.py
luna/lunaClient.py
luna/lunaUtils.py
luna/mlflowLunaUtils.py
luna/numpyJsonEncoder.py
luna/utils.py
luna/dataset/__init__.py
luna/dataset/exceptions.py
luna/dataset/luna_dataset.py
luna/dataset/luna_file_dataset.py
luna/dataset/luna_tabular_dataset.py
luna/logging/__init__.py
luna/logging/azuremlLunaLogger.py
luna/logging/baseLunaLogger.py
luna/logging/localLunaLogger.py
luna/logging/mlflowLunaLogger.py
luna_publish_utils-0.7.3.dist-info/METADATA
luna_publish_utils-0.7.3.dist-info/WHEEL
luna_publish_utils-0.7.3.dist-info/top_level.txt
luna_publish_utils-0.7.3.dist-info/RECORD
